{
  "SearchResults": {
    "ProductCount": "737",
    "Products": [
      {
        "Id": {
          "PartNumber": "04916465000P",
          "SkuPartNumber": "04916465000",
          "CatEntryId": "42662999",
          "MfgPartNumber": "04916465000",
          "KsnValue": "04916465000"
        },
        "Description": {
          "Name": "Delta Children Glenwood 3 In 1 Espresso Convertible Sleigh Crib",
          "BrandName": "Delta Children",
          "ImageURL": "http:\/\/c.shld.net\/rpx\/i\/s\/i\/spin\/image\/spin_prod_494563701",
          "PbType": "NONVARIATION",
          "ReviewRating": {
            "Rating": "3.5",
            "NumReview": "9"
          }
        },
        "Price": {
          "DisplayPrice": "149.99",
          "ClearanceIndicator": "0",
          "PromoInd": "1",
          "IsZipCodeRequired": "false",
          "ShowAKHIMessage": "true"
        },
        "Availability": {
          "StockIndicator": "1",
          "Source": "Online",
          "SpuInd": "true",
          "StsType": "SRES",
          "ResInd": "1"
        },
        "SellerInfo": {
          "StoreOrigin": "S",
          "SellerCount": "1"
        },
        "Fulfillment": {
          "DefaultFullfillment": "DDC",
          "DirectDelivery": "true"
        },
        "OtherInfo": {
          "BeanType": "ProductBean",
          "AutomotiveDivision": "false",
          "NewBundleExperience": "No"
        }
      },
      {
        "Id": {
          "PartNumber": "04902633000P",
          "SkuPartNumber": "04902633000",
          "CatEntryId": "44731612",
          "MfgPartNumber": "74601-616",
          "KsnValue": "04902633000"
        },
        "Description": {
          "Name": "Delta Children Chatham Crib 'N' Changer - Vintage Espresso",
          "BrandName": "Delta Children",
          "ImageURL": "http:\/\/c.shld.net\/rpx\/i\/s\/i\/spin\/image\/spin_prod_1078229212",
          "PbType": "NONVARIATION",
          "ReviewRating": {
            
          }
        },
        "Price": {
          "DisplayPrice": "329.99",
          "ClearanceIndicator": "0",
          "PromoInd": "1",
          "IsZipCodeRequired": "false",
          "ShowAKHIMessage": "true"
        },
        "Availability": {
          "StockIndicator": "1",
          "Source": "Online",
          "SpuInd": "true",
          "StsType": "SRES",
          "ResInd": "1"
        },
        "SellerInfo": {
          "StoreOrigin": "S",
          "SellerCount": "1"
        },
        "Fulfillment": {
          "DefaultFullfillment": "DDC",
          "DirectDelivery": "true"
        },
        "OtherInfo": {
          "BeanType": "ProductBean",
          "AutomotiveDivision": "false",
          "NewBundleExperience": "No"
        }
      },
      {
        "Id": {
          "PartNumber": "04925089000P",
          "SkuPartNumber": "04925089000",
          "CatEntryId": "44367670",
          "MfgPartNumber": "299180-648",
          "KsnValue": "04925089000"
        },
        "Description": {
          "Name": "Delta Children Elite 4-in-1 Crib - Cabernet",
          "BrandName": "Delta Children",
          "ImageURL": "http:\/\/c.shld.net\/rpx\/i\/s\/i\/spin\/image\/spin_prod_935730812",
          "PbType": "NONVARIATION",
          "ReviewRating": {
            
          }
        },
        "Price": {
          "DisplayPrice": "319.99",
          "ClearanceIndicator": "0",
          "PromoInd": "1",
          "IsZipCodeRequired": "false",
          "ShowAKHIMessage": "true"
        },
        "Availability": {
          "StockIndicator": "1",
          "Source": "Online",
          "SpuInd": "true",
          "StsType": "SRES",
          "ResInd": "1"
        },
        "SellerInfo": {
          "StoreOrigin": "S",
          "SellerCount": "1"
        },
        "Fulfillment": {
          "DefaultFullfillment": "DDC",
          "DirectDelivery": "true"
        },
        "OtherInfo": {
          "BeanType": "ProductBean",
          "AutomotiveDivision": "false",
          "NewBundleExperience": "No"
        }
      },
      {
        "Id": {
          "PartNumber": "04916467000P",
          "SkuPartNumber": "04916467000",
          "CatEntryId": "42663000",
          "MfgPartNumber": "04916467000",
          "KsnValue": "04916467000"
        },
        "Description": {
          "Name": "Delta Children Eclipse 4 In 1 Espresso Convertible Crib",
          "BrandName": "Delta Children",
          "ImageURL": "http:\/\/c.shld.net\/rpx\/i\/s\/i\/spin\/image\/spin_prod_494564201",
          "PbType": "NONVARIATION",
          "ReviewRating": {
            "Rating": "4.0",
            "NumReview": "9"
          }
        },
        "Price": {
          "DisplayPrice": "269.99",
          "ClearanceIndicator": "0",
          "PromoInd": "1",
          "IsZipCodeRequired": "false",
          "ShowAKHIMessage": "true"
        },
        "Availability": {
          "StockIndicator": "1",
          "Source": "Online",
          "SpuInd": "true",
          "StsType": "SRES",
          "ResInd": "1"
        },
        "SellerInfo": {
          "StoreOrigin": "S",
          "SellerCount": "1"
        },
        "Fulfillment": {
          "DefaultFullfillment": "DDC",
          "DirectDelivery": "true"
        },
        "OtherInfo": {
          "BeanType": "ProductBean",
          "AutomotiveDivision": "false",
          "NewBundleExperience": "No"
        }
      },
      {
        "Id": {
          "PartNumber": "04925086000P",
          "SkuPartNumber": "04925086000",
          "CatEntryId": "44367672",
          "MfgPartNumber": "7820-648",
          "KsnValue": "04925086000"
        },
        "Description": {
          "Name": "Delta Children Children's Peyton 4-in-1 Crib - Cabernet",
          "BrandName": "Delta Children",
          "ImageURL": "http:\/\/c.shld.net\/rpx\/i\/s\/i\/spin\/image\/spin_prod_935728512",
          "PbType": "NONVARIATION",
          "ReviewRating": {
            "Rating": "5",
            "NumReview": "1"
          }
        },
        "Price": {
          "DisplayPrice": "299.99",
          "ClearanceIndicator": "0",
          "PromoInd": "1",
          "IsZipCodeRequired": "false",
          "ShowAKHIMessage": "true"
        },
        "Availability": {
          "StockIndicator": "1",
          "Source": "Online",
          "SpuInd": "true",
          "StsType": "SRES",
          "ResInd": "1"
        },
        "SellerInfo": {
          "StoreOrigin": "S",
          "SellerCount": "1"
        },
        "Fulfillment": {
          "DefaultFullfillment": "DDC",
          "DirectDelivery": "true"
        },
        "OtherInfo": {
          "BeanType": "ProductBean",
          "AutomotiveDivision": "false",
          "NewBundleExperience": "No"
        }
      },
      {
        "Id": {
          "PartNumber": "04927952000P",
          "SkuPartNumber": "04927952000",
          "CatEntryId": "44807184",
          "MfgPartNumber": "602150-100",
          "KsnValue": "04927952000"
        },
        "Description": {
          "Name": "Delta Children Layla 4-in-1 Crib",
          "BrandName": "Delta Children",
          "ImageURL": "http:\/\/c.shld.net\/rpx\/i\/s\/i\/spin\/image\/spin_prod_1123708212",
          "PbType": "NONVARIATION",
          "ReviewRating": {
            
          }
        },
        "Price": {
          "DisplayPrice": "179.99",
          "ClearanceIndicator": "0",
          "PromoInd": "1",
          "IsZipCodeRequired": "false",
          "ShowAKHIMessage": "true"
        },
        "Availability": {
          "StockIndicator": "1",
          "Source": "Online"
        },
        "SellerInfo": {
          "StoreOrigin": "S",
          "SellerCount": "1"
        },
        "Fulfillment": {
          "DefaultFullfillment": "VD",
          "DirectDelivery": "false",
          "IntShipEligible": "1"
        },
        "OtherInfo": {
          "BeanType": "ProductBean",
          "AutomotiveDivision": "false",
          "NewBundleExperience": "No"
        }
      },
      {
        "Id": {
          "PartNumber": "04922865000P",
          "SkuPartNumber": "04922865000",
          "CatEntryId": "43925210",
          "MfgPartNumber": "552003V",
          "KsnValue": "04922865000"
        },
        "Description": {
          "Name": "Lambs & Ivy TICKLES             3PC CRIB  SET",
          "BrandName": "Lambs & Ivy",
          "ImageURL": "http:\/\/c.shld.net\/rpx\/i\/s\/i\/spin\/image\/spin_prod_849785412",
          "PbType": "NONVARIATION",
          "ReviewRating": {
            
          }
        },
        "Price": {
          "DisplayPrice": "89.99",
          "ClearanceIndicator": "0",
          "PromoInd": "1",
          "IsZipCodeRequired": "false",
          "ShowAKHIMessage": "true"
        },
        "Availability": {
          "StockIndicator": "1",
          "Source": "Online",
          "SpuInd": "true",
          "StsType": "CRES",
          "ResInd": "1",
          "FreeShippingEligible": "True",
          "FreeShippingThreshold": "59"
        },
        "SellerInfo": {
          "StoreOrigin": "S",
          "SellerCount": "1"
        },
        "Fulfillment": {
          "DefaultFullfillment": "TW",
          "DirectDelivery": "false",
          "IntShipEligible": "1"
        },
        "OtherInfo": {
          "BeanType": "ProductBean",
          "AutomotiveDivision": "false",
          "NewBundleExperience": "No"
        }
      },
      {
        "Id": {
          "PartNumber": "04927813000P",
          "SkuPartNumber": "04927813000",
          "CatEntryId": "44681863",
          "MfgPartNumber": "6922-100",
          "KsnValue": "04927813000"
        },
        "Description": {
          "Name": "Delta Children Capri 3-in-1 Crib",
          "BrandName": "Delta Children",
          "ImageURL": "http:\/\/c.shld.net\/rpx\/i\/s\/i\/spin\/image\/spin_prod_1058398212",
          "PbType": "NONVARIATION",
          "ReviewRating": {
            
          }
        },
        "Price": {
          "DisplayPrice": "144.99",
          "ClearanceIndicator": "0",
          "PromoInd": "1",
          "IsZipCodeRequired": "false",
          "ShowAKHIMessage": "true"
        },
        "Availability": {
          "StockIndicator": "1",
          "Source": "Online"
        },
        "SellerInfo": {
          "StoreOrigin": "S",
          "SellerCount": "1"
        },
        "Fulfillment": {
          "DefaultFullfillment": "VD",
          "DirectDelivery": "false",
          "IntShipEligible": "1"
        },
        "OtherInfo": {
          "BeanType": "ProductBean",
          "AutomotiveDivision": "false",
          "NewBundleExperience": "No"
        }
      },
      {
        "Id": {
          "PartNumber": "04928946000P",
          "SkuPartNumber": "04928946000",
          "CatEntryId": "45005852",
          "MfgPartNumber": "04510-281",
          "KsnValue": "04928946000"
        },
        "Description": {
          "Name": "Stork Craft Sheffield Convertible Crib - White",
          "BrandName": "Stork Craft",
          "ImageURL": "http:\/\/c.shld.net\/rpx\/i\/s\/i\/spin\/image\/spin_prod_1323183912",
          "PbType": "NONVARIATION",
          "ReviewRating": {
            
          }
        },
        "Price": {
          "DisplayPrice": "129.99",
          "ClearanceIndicator": "0",
          "PromoInd": "1",
          "IsZipCodeRequired": "false",
          "ShowAKHIMessage": "true"
        },
        "Availability": {
          "StockIndicator": "1",
          "Source": "Online"
        },
        "SellerInfo": {
          "StoreOrigin": "S",
          "SellerCount": "1"
        },
        "Fulfillment": {
          "DefaultFullfillment": "VD",
          "DirectDelivery": "false",
          "IntShipEligible": "1"
        },
        "OtherInfo": {
          "BeanType": "ProductBean",
          "AutomotiveDivision": "false",
          "NewBundleExperience": "No"
        }
      },
      {
        "Id": {
          "PartNumber": "024W005320517001P",
          "SkuPartNumber": "024W005320517001",
          "CatEntryId": "2068698",
          "MfgPartNumber": "67570",
          "KsnValue": "024W005320517001"
        },
        "Description": {
          "Name": "Summer Infants Jungles Buddies 4pc Crib Set",
          "BrandName": "Summer Infants",
          "ImageURL": "http:\/\/c.shld.net\/rpx\/i\/s\/i\/spin\/image\/spin_prod_776260412",
          "PbType": "NONVARIATION",
          "ReviewRating": {
            "Rating": "4.0",
            "NumReview": "4"
          }
        },
        "Price": {
          "CutPrice": "59.99",
          "DisplayPrice": "53.99",
          "ClearanceIndicator": "0",
          "PromoInd": "1",
          "IsZipCodeRequired": "false",
          "ShowAKHIMessage": "true"
        },
        "Availability": {
          "SaleIndicator": "1",
          "StockIndicator": "1",
          "Source": "Online",
          "SpuInd": "true",
          "StsType": "DRES",
          "ResInd": "1",
          "FreeShippingEligible": "True",
          "FreeShippingThreshold": "59"
        },
        "SellerInfo": {
          "StoreOrigin": "K",
          "SellerCount": "1"
        },
        "Fulfillment": {
          "DefaultFullfillment": "TW",
          "DirectDelivery": "false",
          "IntShipEligible": "1"
        },
        "OtherInfo": {
          "BeanType": "ProductBean",
          "AutomotiveDivision": "false",
          "NewBundleExperience": "No"
        }
      },
      {
        "Id": {
          "PartNumber": "04918029000P",
          "SkuPartNumber": "04918029000",
          "CatEntryId": "42914274",
          "MfgPartNumber": "1962077",
          "KsnValue": "04918029000"
        },
        "Description": {
          "Name": "Foundations Evacuation Frame with Antique Brass Casters for Natural SafetyCraft, Serenity and Biltmore Compact Cribs",
          "BrandName": "Foundations",
          "ImageURL": "http:\/\/c.shld.net\/rpx\/i\/s\/i\/spin\/image\/spin_prod_256970201",
          "PbType": "NONVARIATION",
          "ReviewRating": {
            
          }
        },
        "Price": {
          "DisplayPrice": "69.90",
          "ClearanceIndicator": "0",
          "PromoInd": "1",
          "IsZipCodeRequired": "false",
          "ShowAKHIMessage": "true"
        },
        "Availability": {
          "StockIndicator": "1",
          "Source": "Online",
          "FreeShippingEligible": "True",
          "FreeShippingThreshold": "59"
        },
        "SellerInfo": {
          "StoreOrigin": "S",
          "SellerCount": "1"
        },
        "Fulfillment": {
          "DefaultFullfillment": "VD",
          "DirectDelivery": "false",
          "IntShipEligible": "1"
        },
        "OtherInfo": {
          "BeanType": "ProductBean",
          "AutomotiveDivision": "false",
          "NewBundleExperience": "No"
        }
      },
      {
        "Id": {
          "PartNumber": "04918039000P",
          "SkuPartNumber": "04918039000",
          "CatEntryId": "42914292",
          "MfgPartNumber": "1031042",
          "KsnValue": "04918039000"
        },
        "Description": {
          "Name": "Foundations HideAway Folding, Fixed Side, Compact Crib Natural",
          "BrandName": "Foundations",
          "ImageURL": "http:\/\/c.shld.net\/rpx\/i\/s\/i\/spin\/image\/spin_prod_256982901",
          "PbType": "NONVARIATION",
          "ReviewRating": {
            
          }
        },
        "Price": {
          "DisplayPrice": "249.90",
          "ClearanceIndicator": "0",
          "PromoInd": "1",
          "IsZipCodeRequired": "false",
          "ShowAKHIMessage": "true"
        },
        "Availability": {
          "SaleIndicator": "1",
          "StockIndicator": "1",
          "Source": "Online",
          "FreeShippingEligible": "True",
          "FreeShippingThreshold": "59"
        },
        "SellerInfo": {
          "StoreOrigin": "S",
          "SellerCount": "1"
        },
        "Fulfillment": {
          "DefaultFullfillment": "VD",
          "DirectDelivery": "false",
          "IntShipEligible": "1"
        },
        "OtherInfo": {
          "BeanType": "ProductBean",
          "AutomotiveDivision": "false",
          "NewBundleExperience": "No"
        }
      },
      {
        "Id": {
          "PartNumber": "04926809000P",
          "SkuPartNumber": "04926809000",
          "CatEntryId": "44476947",
          "MfgPartNumber": "180120-648",
          "KsnValue": "04926809000"
        },
        "Description": {
          "Name": "Simmons Kids Toddler Guard Rail for the Elite Crib",
          "BrandName": "Simmons Kids",
          "ImageURL": "http:\/\/c.shld.net\/rpx\/i\/s\/i\/spin\/image\/spin_prod_968501612",
          "PbType": "NONVARIATION",
          "ReviewRating": {
            
          }
        },
        "Price": {
          "DisplayPrice": "92.99",
          "ClearanceIndicator": "0",
          "PromoInd": "1",
          "IsZipCodeRequired": "false",
          "ShowAKHIMessage": "true"
        },
        "Availability": {
          "StockIndicator": "1",
          "Source": "Online",
          "SpuInd": "true",
          "StsType": "VRES",
          "ResInd": "1",
          "FreeShippingEligible": "True",
          "FreeShippingThreshold": "59"
        },
        "SellerInfo": {
          "StoreOrigin": "S",
          "SellerCount": "1"
        },
        "Fulfillment": {
          "DefaultFullfillment": "VD",
          "DirectDelivery": "false",
          "IntShipEligible": "1"
        },
        "OtherInfo": {
          "BeanType": "ProductBean",
          "AutomotiveDivision": "false",
          "NewBundleExperience": "No"
        }
      },
      {
        "Id": {
          "PartNumber": "04922873000P",
          "SkuPartNumber": "04922873000",
          "CatEntryId": "43655279",
          "MfgPartNumber": "0040-990",
          "KsnValue": "04922873000"
        },
        "Description": {
          "Name": "Delta Children Crib Conversion Rails",
          "BrandName": "Delta Children",
          "ImageURL": "http:\/\/c.shld.net\/rpx\/i\/s\/i\/spin\/image\/spin_prod_786369212",
          "PbType": "NONVARIATION",
          "ReviewRating": {
            
          }
        },
        "Price": {
          "CutPrice": "69.99",
          "DisplayPrice": "58.82",
          "ClearanceIndicator": "0",
          "PromoInd": "1",
          "IsZipCodeRequired": "false",
          "ShowAKHIMessage": "true"
        },
        "Availability": {
          "SaleIndicator": "1",
          "StockIndicator": "1",
          "Source": "Online",
          "SpuInd": "true",
          "StsType": "VRES",
          "ResInd": "1",
          "FreeShippingEligible": "True",
          "FreeShippingThreshold": "59"
        },
        "SellerInfo": {
          "StoreOrigin": "S",
          "SellerCount": "1"
        },
        "Fulfillment": {
          "DefaultFullfillment": "VD",
          "DirectDelivery": "false",
          "IntShipEligible": "1"
        },
        "OtherInfo": {
          "BeanType": "ProductBean",
          "AutomotiveDivision": "false",
          "NewBundleExperience": "No"
        }
      },
      {
        "Id": {
          "PartNumber": "04902681000P",
          "SkuPartNumber": "04902681000",
          "CatEntryId": "44478833",
          "MfgPartNumber": "0080-627",
          "KsnValue": "04902681000"
        },
        "Description": {
          "Name": "Delta Children GUARDRAIL FOR Columbia 3 in 1 Crib and Catalina 4 in 1 Crib  in Betony Cherry",
          "BrandName": "Delta Children",
          "ImageURL": "http:\/\/c.shld.net\/rpx\/i\/s\/i\/spin\/image\/spin_prod_968618812",
          "PbType": "NONVARIATION",
          "ReviewRating": {
            
          }
        },
        "Price": {
          "DisplayPrice": "59.99",
          "ClearanceIndicator": "0",
          "PromoInd": "1",
          "IsZipCodeRequired": "false",
          "ShowAKHIMessage": "true"
        },
        "Availability": {
          "StockIndicator": "1",
          "Source": "Online",
          "SpuInd": "true",
          "StsType": "VRES",
          "ResInd": "1",
          "FreeShippingEligible": "True",
          "FreeShippingThreshold": "59"
        },
        "SellerInfo": {
          "StoreOrigin": "S",
          "SellerCount": "1"
        },
        "Fulfillment": {
          "DefaultFullfillment": "VD",
          "DirectDelivery": "false",
          "IntShipEligible": "1"
        },
        "OtherInfo": {
          "BeanType": "ProductBean",
          "AutomotiveDivision": "false",
          "NewBundleExperience": "No"
        }
      },
      {
        "Id": {
          "PartNumber": "04927394000P",
          "SkuPartNumber": "04927394000",
          "CatEntryId": "44532310",
          "MfgPartNumber": "1965202",
          "KsnValue": "04927394000"
        },
        "Description": {
          "Name": "Foundations Steel Crib Evacuation Kit (Four 4\" casters)",
          "BrandName": "Foundations",
          "ImageURL": "http:\/\/c.shld.net\/rpx\/i\/s\/i\/spin\/image\/spin_prod_981167712",
          "PbType": "NONVARIATION",
          "ReviewRating": {
            
          }
        },
        "Price": {
          "DisplayPrice": "34.99",
          "ClearanceIndicator": "0",
          "PromoInd": "1",
          "IsZipCodeRequired": "false",
          "ShowAKHIMessage": "true"
        },
        "Availability": {
          "StockIndicator": "1",
          "Source": "Online",
          "FreeShippingEligible": "True",
          "FreeShippingThreshold": "59"
        },
        "SellerInfo": {
          "StoreOrigin": "S",
          "SellerCount": "1"
        },
        "Fulfillment": {
          "DefaultFullfillment": "VD",
          "DirectDelivery": "false",
          "IntShipEligible": "1"
        },
        "OtherInfo": {
          "BeanType": "ProductBean",
          "AutomotiveDivision": "false",
          "NewBundleExperience": "No"
        }
      },
      {
        "Id": {
          "PartNumber": "04924198000P",
          "SkuPartNumber": "04924198000",
          "CatEntryId": "43909368",
          "MfgPartNumber": "1743040",
          "KsnValue": "04924198000"
        },
        "Description": {
          "Name": "Foundations Serenity SafeReach Compact Crib, Mirror End, Natural",
          "BrandName": "Foundations",
          "ImageURL": "http:\/\/c.shld.net\/rpx\/i\/s\/i\/spin\/image\/spin_prod_844127612",
          "PbType": "NONVARIATION",
          "ReviewRating": {
            
          }
        },
        "Price": {
          "DisplayPrice": "259.90",
          "ClearanceIndicator": "0",
          "PromoInd": "1",
          "IsZipCodeRequired": "false",
          "ShowAKHIMessage": "true"
        },
        "Availability": {
          "StockIndicator": "1",
          "Source": "Online",
          "FreeShippingEligible": "True",
          "FreeShippingThreshold": "59"
        },
        "SellerInfo": {
          "StoreOrigin": "S",
          "SellerCount": "1"
        },
        "Fulfillment": {
          "DefaultFullfillment": "VD",
          "DirectDelivery": "false",
          "IntShipEligible": "1"
        },
        "OtherInfo": {
          "BeanType": "ProductBean",
          "AutomotiveDivision": "false",
          "NewBundleExperience": "No"
        }
      },
      {
        "Id": {
          "PartNumber": "04918933000P",
          "SkuPartNumber": "04918933000",
          "CatEntryId": "42969374",
          "MfgPartNumber": "0081-645",
          "KsnValue": "04918933000"
        },
        "Description": {
          "Name": "Delta Children GUARDRAIL FOR Eclipse 4 n 1 Crib in Espresso Java",
          "BrandName": "Delta Children",
          "ImageURL": "http:\/\/c.shld.net\/rpx\/i\/s\/i\/spin\/image\/spin_prod_539713701",
          "PbType": "NONVARIATION",
          "ReviewRating": {
            "Rating": "1.0",
            "NumReview": "1"
          }
        },
        "Price": {
          "DisplayPrice": "59.99",
          "ClearanceIndicator": "0",
          "PromoInd": "1",
          "IsZipCodeRequired": "false",
          "ShowAKHIMessage": "true"
        },
        "Availability": {
          "StockIndicator": "1",
          "Source": "Online",
          "SpuInd": "true",
          "StsType": "VRES",
          "ResInd": "1",
          "FreeShippingEligible": "True",
          "FreeShippingThreshold": "59"
        },
        "SellerInfo": {
          "StoreOrigin": "S",
          "SellerCount": "1"
        },
        "Fulfillment": {
          "DefaultFullfillment": "VD",
          "DirectDelivery": "false",
          "IntShipEligible": "1"
        },
        "OtherInfo": {
          "BeanType": "ProductBean",
          "AutomotiveDivision": "false",
          "NewBundleExperience": "No"
        }
      },
      {
        "Id": {
          "PartNumber": "04918929000P",
          "SkuPartNumber": "04918929000",
          "CatEntryId": "42969377",
          "MfgPartNumber": "0080-607",
          "KsnValue": "04918929000"
        },
        "Description": {
          "Name": "Delta Children GUARDRAIL FOR Columbia 3 in 1 Crib, Catalina 4 in 1 Crib and Lil' Princess Canopy Crib in Black Cherry",
          "BrandName": "Delta Children",
          "ImageURL": "http:\/\/c.shld.net\/rpx\/i\/s\/i\/spin\/image\/spin_prod_539713801",
          "PbType": "NONVARIATION",
          "ReviewRating": {
            
          }
        },
        "Price": {
          "DisplayPrice": "59.99",
          "ClearanceIndicator": "0",
          "PromoInd": "1",
          "IsZipCodeRequired": "false",
          "ShowAKHIMessage": "true"
        },
        "Availability": {
          "StockIndicator": "1",
          "Source": "Online",
          "SpuInd": "true",
          "StsType": "VRES",
          "ResInd": "1",
          "FreeShippingEligible": "True",
          "FreeShippingThreshold": "59"
        },
        "SellerInfo": {
          "StoreOrigin": "S",
          "SellerCount": "1"
        },
        "Fulfillment": {
          "DefaultFullfillment": "VD",
          "DirectDelivery": "false",
          "IntShipEligible": "1"
        },
        "OtherInfo": {
          "BeanType": "ProductBean",
          "AutomotiveDivision": "false",
          "NewBundleExperience": "No"
        }
      },
      {
        "Id": {
          "PartNumber": "04926136000P",
          "SkuPartNumber": "04926136000",
          "CatEntryId": "44387733",
          "MfgPartNumber": "4440-260",
          "KsnValue": "04926136000"
        },
        "Description": {
          "Name": "Delta Children Cozy Crib Americana in Natural",
          "BrandName": "Delta Children",
          "ImageURL": "http:\/\/c.shld.net\/rpx\/i\/s\/i\/spin\/image\/spin_prod_941772012",
          "PbType": "NONVARIATION",
          "ReviewRating": {
            
          }
        },
        "Price": {
          "DisplayPrice": "214.99",
          "ClearanceIndicator": "0",
          "PromoInd": "1",
          "IsZipCodeRequired": "false",
          "ShowAKHIMessage": "true"
        },
        "Availability": {
          "StockIndicator": "1",
          "Source": "Online",
          "SpuInd": "true",
          "StsType": "VRES",
          "ResInd": "1",
          "FreeShippingEligible": "True",
          "FreeShippingThreshold": "59"
        },
        "SellerInfo": {
          "StoreOrigin": "S",
          "SellerCount": "1"
        },
        "Fulfillment": {
          "DefaultFullfillment": "VD",
          "DirectDelivery": "false",
          "IntShipEligible": "1"
        },
        "OtherInfo": {
          "BeanType": "ProductBean",
          "AutomotiveDivision": "false",
          "NewBundleExperience": "No"
        }
      },
      {
        "Id": {
          "PartNumber": "04902896000P",
          "SkuPartNumber": "04902896000",
          "CatEntryId": "45005822",
          "MfgPartNumber": "04550-02D",
          "KsnValue": "04902896000"
        },
        "Description": {
          "Name": "Stork Craft Sorrento Lifestyle Crib - Dove Brown",
          "BrandName": "Stork Craft",
          "ImageURL": "http:\/\/c.shld.net\/rpx\/i\/s\/i\/spin\/image\/spin_prod_1323187312",
          "PbType": "NONVARIATION",
          "ReviewRating": {
            
          }
        },
        "Price": {
          "DisplayPrice": "249.99",
          "ClearanceIndicator": "0",
          "PromoInd": "1",
          "IsZipCodeRequired": "false",
          "ShowAKHIMessage": "true"
        },
        "Availability": {
          "StockIndicator": "1",
          "Source": "Online"
        },
        "SellerInfo": {
          "StoreOrigin": "S",
          "SellerCount": "1"
        },
        "Fulfillment": {
          "DefaultFullfillment": "VD",
          "DirectDelivery": "false",
          "IntShipEligible": "1"
        },
        "OtherInfo": {
          "BeanType": "ProductBean",
          "AutomotiveDivision": "false",
          "NewBundleExperience": "No"
        }
      },
      {
        "Id": {
          "PartNumber": "04918026000P",
          "SkuPartNumber": "04918026000",
          "CatEntryId": "42914289",
          "MfgPartNumber": "1631040",
          "KsnValue": "04918026000"
        },
        "Description": {
          "Name": "Foundations SafetyCraft Compact Fixed Side Slatted Crib",
          "BrandName": "Foundations",
          "ImageURL": "http:\/\/c.shld.net\/rpx\/i\/s\/i\/spin\/image\/spin_prod_256968501",
          "PbType": "NONVARIATION",
          "ReviewRating": {
            
          }
        },
        "Price": {
          "DisplayPrice": "189.90",
          "ClearanceIndicator": "0",
          "PromoInd": "1",
          "IsZipCodeRequired": "false",
          "ShowAKHIMessage": "true"
        },
        "Availability": {
          "StockIndicator": "1",
          "Source": "Online",
          "FreeShippingEligible": "True",
          "FreeShippingThreshold": "59"
        },
        "SellerInfo": {
          "StoreOrigin": "S",
          "SellerCount": "1"
        },
        "Fulfillment": {
          "DefaultFullfillment": "VD",
          "DirectDelivery": "false",
          "IntShipEligible": "1"
        },
        "OtherInfo": {
          "BeanType": "ProductBean",
          "AutomotiveDivision": "false",
          "NewBundleExperience": "No"
        }
      },
      {
        "Id": {
          "PartNumber": "04927954000P",
          "SkuPartNumber": "04927954000",
          "CatEntryId": "44806452",
          "MfgPartNumber": "603150-100",
          "KsnValue": "04927954000"
        },
        "Description": {
          "Name": "Delta Children Remi 4-in-1 Crib",
          "BrandName": "Delta Children",
          "ImageURL": "http:\/\/c.shld.net\/rpx\/i\/s\/i\/spin\/image\/spin_prod_1123713312",
          "PbType": "NONVARIATION",
          "ReviewRating": {
            
          }
        },
        "Price": {
          "DisplayPrice": "199.99",
          "ClearanceIndicator": "0",
          "PromoInd": "1",
          "IsZipCodeRequired": "false",
          "ShowAKHIMessage": "true"
        },
        "Availability": {
          "StockIndicator": "1",
          "Source": "Online"
        },
        "SellerInfo": {
          "StoreOrigin": "S",
          "SellerCount": "1"
        },
        "Fulfillment": {
          "DefaultFullfillment": "VD",
          "DirectDelivery": "false",
          "IntShipEligible": "1"
        },
        "OtherInfo": {
          "BeanType": "ProductBean",
          "AutomotiveDivision": "false",
          "NewBundleExperience": "No"
        }
      },
      {
        "Id": {
          "PartNumber": "04902897000P",
          "SkuPartNumber": "04902897000",
          "CatEntryId": "45005850",
          "MfgPartNumber": "04587-25D",
          "KsnValue": "04902897000"
        },
        "Description": {
          "Name": "Stork Craft Valentia Convertible Crib - Dove Brown",
          "BrandName": "Stork Craft",
          "ImageURL": "http:\/\/c.shld.net\/rpx\/i\/s\/i\/spin\/image\/spin_prod_1323190712",
          "PbType": "NONVARIATION",
          "ReviewRating": {
            
          }
        },
        "Price": {
          "DisplayPrice": "259.99",
          "ClearanceIndicator": "0",
          "PromoInd": "1",
          "IsZipCodeRequired": "false",
          "ShowAKHIMessage": "true"
        },
        "Availability": {
          "StockIndicator": "1",
          "Source": "Online"
        },
        "SellerInfo": {
          "StoreOrigin": "S",
          "SellerCount": "1"
        },
        "Fulfillment": {
          "DefaultFullfillment": "VD",
          "DirectDelivery": "false",
          "IntShipEligible": "1"
        },
        "OtherInfo": {
          "BeanType": "ProductBean",
          "AutomotiveDivision": "false",
          "NewBundleExperience": "No"
        }
      },
      {
        "Id": {
          "PartNumber": "04928977000P",
          "SkuPartNumber": "04928977000",
          "CatEntryId": "45005752",
          "MfgPartNumber": "04587-48D",
          "KsnValue": "04928977000"
        },
        "Description": {
          "Name": "Stork Craft Verona Convertible Crib - Dove Brown",
          "BrandName": "Stork Craft",
          "ImageURL": "http:\/\/c.shld.net\/rpx\/i\/s\/i\/spin\/image\/spin_prod_1323192612",
          "PbType": "NONVARIATION",
          "ReviewRating": {
            
          }
        },
        "Price": {
          "DisplayPrice": "249.99",
          "ClearanceIndicator": "0",
          "PromoInd": "1",
          "IsZipCodeRequired": "false",
          "ShowAKHIMessage": "true"
        },
        "Availability": {
          "StockIndicator": "1",
          "Source": "Online"
        },
        "SellerInfo": {
          "StoreOrigin": "S",
          "SellerCount": "1"
        },
        "Fulfillment": {
          "DefaultFullfillment": "VD",
          "DirectDelivery": "false",
          "IntShipEligible": "1"
        },
        "OtherInfo": {
          "BeanType": "ProductBean",
          "AutomotiveDivision": "false",
          "NewBundleExperience": "No"
        }
      }
    ],
    "FilterProducts": [
      {
        "FilterKey": "Brand",
        "FilterValues": [
          {
            "Name": "Sweet Jojo Designs",
            "FilterIndex": "0",
            "ContentCount": "303"
          },
          {
            "Name": "Trend Lab",
            "FilterIndex": "1",
            "ContentCount": "165"
          },
          {
            "Name": "Cotton Tale",
            "FilterIndex": "2",
            "ContentCount": "42"
          },
          {
            "Name": "Carter's",
            "FilterIndex": "3",
            "ContentCount": "39"
          },
          {
            "Name": "Delta Children",
            "FilterIndex": "4",
            "ContentCount": "31"
          },
          {
            "Name": "GEENNY",
            "FilterIndex": "5",
            "ContentCount": "30"
          },
          {
            "Name": "Lambs & Ivy",
            "FilterIndex": "6",
            "ContentCount": "20"
          },
          {
            "Name": "Foundations",
            "FilterIndex": "7",
            "ContentCount": "13"
          },
          {
            "Name": "Stork Craft",
            "FilterIndex": "8",
            "ContentCount": "10"
          },
          {
            "Name": "Disney",
            "FilterIndex": "9",
            "ContentCount": "7"
          },
          {
            "Name": "Disney Baby",
            "FilterIndex": "10",
            "ContentCount": "7"
          },
          {
            "Name": "Kidsline",
            "FilterIndex": "11",
            "ContentCount": "7"
          },
          {
            "Name": "L.A. Baby",
            "FilterIndex": "12",
            "ContentCount": "7"
          },
          {
            "Name": "Graco",
            "FilterIndex": "13",
            "ContentCount": "6"
          },
          {
            "Name": "Sealy",
            "FilterIndex": "14",
            "ContentCount": "6"
          },
          {
            "Name": "CafePress",
            "FilterIndex": "15",
            "ContentCount": "4"
          },
          {
            "Name": "Dorel Home Furnishings",
            "FilterIndex": "16",
            "ContentCount": "4"
          },
          {
            "Name": "Piyo Piyo USA",
            "FilterIndex": "17",
            "ContentCount": "4"
          },
          {
            "Name": "Summer Infants",
            "FilterIndex": "18",
            "ContentCount": "4"
          },
          {
            "Name": "Tiny Love",
            "FilterIndex": "19",
            "ContentCount": "4"
          },
          {
            "Name": "Rashti & Rashti",
            "FilterIndex": "20",
            "ContentCount": "3"
          },
          {
            "Name": "Summer Infant",
            "FilterIndex": "21",
            "ContentCount": "3"
          }
        ]
      },
      {
        "FilterKey": "clearance",
        "FilterValues": [
          {
            "Name": "Yes",
            "FilterIndex": "22",
            "ContentCount": "8"
          }
        ]
      },
      {
        "FilterKey": "delivery",
        "FilterValues": [
          {
            "Name": "1",
            "FilterIndex": "23",
            "ContentCount": "6"
          }
        ]
      },
      {
        "FilterKey": "discount",
        "FilterValues": [
          {
            "Name": "1",
            "FilterIndex": "24",
            "ContentCount": "149"
          },
          {
            "Name": "20",
            "FilterIndex": "25",
            "ContentCount": "64"
          },
          {
            "Name": "30",
            "FilterIndex": "26",
            "ContentCount": "16"
          }
        ]
      },
      {
        "FilterKey": "freeDelivery",
        "FilterValues": [
          
        ]
      },
      {
        "FilterKey": "freeShipping",
        "FilterValues": [
          {
            "Name": "0",
            "FilterIndex": "27",
            "ContentCount": "32"
          },
          {
            "Name": "1",
            "FilterIndex": "28",
            "ContentCount": "705"
          }
        ]
      },
      {
        "FilterKey": "fulfillment",
        "FilterValues": [
          
        ]
      },
      {
        "FilterKey": "has991",
        "FilterValues": [
          
        ]
      },
      {
        "FilterKey": "international_shipping",
        "FilterValues": [
          {
            "Name": "0",
            "FilterIndex": "29",
            "ContentCount": "725"
          },
          {
            "Name": "1",
            "FilterIndex": "30",
            "ContentCount": "725"
          },
          {
            "Name": "10",
            "FilterIndex": "31",
            "ContentCount": "725"
          },
          {
            "Name": "3",
            "FilterIndex": "32",
            "ContentCount": "340"
          },
          {
            "Name": "5",
            "FilterIndex": "33",
            "ContentCount": "706"
          },
          {
            "Name": "6",
            "FilterIndex": "34",
            "ContentCount": "725"
          },
          {
            "Name": "7",
            "FilterIndex": "35",
            "ContentCount": "725"
          },
          {
            "Name": "8",
            "FilterIndex": "36",
            "ContentCount": "725"
          },
          {
            "Name": "9",
            "FilterIndex": "37",
            "ContentCount": "725"
          }
        ]
      },
      {
        "FilterKey": "itemCondition",
        "FilterValues": [
          {
            "Name": "New",
            "FilterIndex": "38",
            "ContentCount": "735"
          }
        ]
      },
      {
        "FilterKey": "layAway",
        "FilterValues": [
          {
            "Name": "0",
            "FilterIndex": "39",
            "ContentCount": "641"
          },
          {
            "Name": "1",
            "FilterIndex": "40",
            "ContentCount": "96"
          }
        ]
      },
      {
        "FilterKey": "mailInRebate",
        "FilterValues": [
          
        ]
      },
      {
        "FilterKey": "new",
        "FilterValues": [
          {
            "Name": "30",
            "FilterIndex": "41",
            "ContentCount": "14"
          },
          {
            "Name": "60",
            "FilterIndex": "42",
            "ContentCount": "38"
          },
          {
            "Name": "90",
            "FilterIndex": "43",
            "ContentCount": "48"
          }
        ]
      },
      {
        "FilterKey": "offer",
        "FilterValues": [
          {
            "Name": "Companion",
            "FilterIndex": "44",
            "ContentCount": "734"
          },
          {
            "Name": "Free Shipping",
            "FilterIndex": "45",
            "ContentCount": "705"
          },
          {
            "Name": "All Items On Sale",
            "FilterIndex": "46",
            "ContentCount": "143"
          },
          {
            "Name": "Clearance",
            "FilterIndex": "47",
            "ContentCount": "8"
          }
        ]
      },
      {
        "FilterKey": "sale",
        "FilterValues": [
          {
            "Name": "Yes",
            "FilterIndex": "48",
            "ContentCount": "143"
          }
        ]
      },
      {
        "FilterKey": "sears_international",
        "FilterValues": [
          {
            "Name": "YES",
            "FilterIndex": "49",
            "ContentCount": "729"
          }
        ]
      },
      {
        "FilterKey": "shipping",
        "FilterValues": [
          {
            "Name": "1",
            "FilterIndex": "50",
            "ContentCount": "698"
          }
        ]
      },
      {
        "FilterKey": "shipVantage",
        "FilterValues": [
          {
            "Name": "1",
            "FilterIndex": "51",
            "ContentCount": "704"
          }
        ]
      },
      {
        "FilterKey": "spuEligible",
        "FilterValues": [
          {
            "Name": "Yes",
            "FilterIndex": "52",
            "ContentCount": "85"
          }
        ]
      },
      {
        "FilterKey": "storeOrigin",
        "FilterValues": [
          {
            "Name": "Sears",
            "FilterIndex": "53",
            "ContentCount": "714"
          },
          {
            "Name": "Kmart",
            "FilterIndex": "54",
            "ContentCount": "23"
          },
          {
            "Name": "Overstock.com",
            "FilterIndex": "55",
            "ContentCount": "1"
          }
        ]
      },
      {
        "FilterKey": "trustedSeller",
        "FilterValues": [
          
        ]
      }
    ],
    "FilterRanks": [
      {
        "Name": "Brand",
        "Rank": "1"
      },
      {
        "Name": "Price",
        "Rank": "2"
      },
      {
        "Name": "offer",
        "Rank": "3"
      },
      {
        "Name": "discount",
        "Rank": "4"
      },
      {
        "Name": "Promotions",
        "Rank": "5"
      },
      {
        "Name": "clearance",
        "Rank": "99"
      },
      {
        "Name": "delivery",
        "Rank": "99"
      },
      {
        "Name": "freeDelivery",
        "Rank": "99"
      },
      {
        "Name": "freeShipping",
        "Rank": "99"
      },
      {
        "Name": "fulfillment",
        "Rank": "99"
      },
      {
        "Name": "has991",
        "Rank": "99"
      },
      {
        "Name": "international_shipping",
        "Rank": "99"
      },
      {
        "Name": "itemCondition",
        "Rank": "99"
      },
      {
        "Name": "layAway",
        "Rank": "99"
      },
      {
        "Name": "mailInRebate",
        "Rank": "99"
      },
      {
        "Name": "new",
        "Rank": "99"
      },
      {
        "Name": "sale",
        "Rank": "99"
      },
      {
        "Name": "sears_international",
        "Rank": "99"
      },
      {
        "Name": "shipping",
        "Rank": "99"
      },
      {
        "Name": "shipVantage",
        "Rank": "99"
      },
      {
        "Name": "spuEligible",
        "Rank": "99"
      },
      {
        "Name": "trustedSeller",
        "Rank": "99"
      },
      {
        "Name": "Rating",
        "Rank": "995"
      },
      {
        "Name": "storeOrigin",
        "Rank": "996"
      },
      {
        "Name": "filterShipping",
        "Rank": "997"
      },
      {
        "Name": "condition",
        "Rank": "998"
      },
      {
        "Name": "rebate",
        "Rank": "999"
      }
    ],
    "Categories": [
      {
        "ProdCountAggr": "737",
        "KeyWord": "cribs",
        "Name": "Baby",
        "Category": "Baby"
      }
    ],
    "Status": {
      "ResponseCode": "0",
      "RespMessage": "Successful"
    },
    "ApiTracking": "Server: PROD-SERVER-404-1|Tracking ID: {1429714045502}|API Client Session Key: 4416888942867161892|Time : Wed Apr 22 09:47:26 CDT 2015|UID : 4416888942867161892|From Cache : N"
  }
}
